moat/lib/broadcast/__init__.py
moat/lib/broadcast/_impl.py
moat_lib_broadcast-0.1.2.dist-info/licenses/LICENSE.txt
moat_lib_broadcast-0.1.2.dist-info/METADATA
moat_lib_broadcast-0.1.2.dist-info/WHEEL
moat_lib_broadcast-0.1.2.dist-info/top_level.txt
moat_lib_broadcast-0.1.2.dist-info/RECORD
