Metadata-Version: 2.4
Name: moat-lib-broadcast
Version: 0.1.2
Summary: Broadcasting support for MoaT applications
Maintainer-email: Matthias Urlichs <matthias@urlichs.de>
Project-URL: homepage, https://m-o-a-t.org
Project-URL: repository, https://github.com/M-o-a-T/moat
Keywords: MoaT
Classifier: Development Status :: 4 - Beta
Classifier: Framework :: AnyIO
Classifier: Framework :: Trio
Classifier: Framework :: AsyncIO
Classifier: Programming Language :: Python :: 3
Classifier: Intended Audience :: Developers
Requires-Python: >=3.8
License-File: LICENSE.txt
Requires-Dist: moat-util~=0.62.2
Requires-Dist: moat-lib-micro~=0.2.1
Requires-Dist: attrs~=23.0
Dynamic: license-file
